testpypizhangxin/__init__.py
testpypizhangxin/day.py
testpublishzhangxin-0.0.4.dist-info/METADATA
testpublishzhangxin-0.0.4.dist-info/WHEEL
testpublishzhangxin-0.0.4.dist-info/top_level.txt
testpublishzhangxin-0.0.4.dist-info/RECORD
